setup.py
distributions_of_probability/Binomialdistribution.py
distributions_of_probability/Gaussiandistribution.py
distributions_of_probability/Generaldistribution.py
distributions_of_probability/__init__.py
distributions_of_probability.egg-info/PKG-INFO
distributions_of_probability.egg-info/SOURCES.txt
distributions_of_probability.egg-info/dependency_links.txt
distributions_of_probability.egg-info/not-zip-safe
distributions_of_probability.egg-info/top_level.txt